prepify/__init__.py
prepify/__main__.py
prepify/Prepify.py
prepify/py/__init__.py
prepify/py/backup.py
prepify/py/document_layout.py
prepify/py/edit_foliation_window.py
prepify/py/edit_pages.py
prepify/py/edit_settings.py
prepify/py/export_to_docx.py
prepify/py/foliation.py
prepify/py/guide_sheet.py
prepify/py/liste.py
prepify/py/load_liste.py
prepify/py/package.py
prepify/py/quires.py
prepify/py/read_doc_form.py
prepify/py/tips.py
prepify/resources/new.csntm
prepify/resources/prepdoc_template.docx
prepify-0.10.1.dist-info/WHEEL
prepify-0.10.1.dist-info/METADATA
prepify-0.10.1.dist-info/RECORD
